{"v":5,"entries":{"inputs-buttons-solid-button--docs":{"id":"inputs-buttons-solid-button--docs","title":"Inputs/Buttons/Solid Button","name":"Docs","importPath":"./stories/Button.stories.js","type":"docs","tags":["dev","test","autodocs"],"storiesImports":[]},"inputs-buttons-solid-button--default":{"type":"story","id":"inputs-buttons-solid-button--default","name":"Default","title":"Inputs/Buttons/Solid Button","importPath":"./stories/Button.stories.js","tags":["dev","test","autodocs"]},"inputs-buttons-solid-button--intent":{"type":"story","id":"inputs-buttons-solid-button--intent","name":"Intent","title":"Inputs/Buttons/Solid Button","importPath":"./stories/Button.stories.js","tags":["dev","test","autodocs"]},"inputs-buttons-solid-button--size":{"type":"story","id":"inputs-buttons-solid-button--size","name":"Size","title":"Inputs/Buttons/Solid Button","importPath":"./stories/Button.stories.js","tags":["dev","test","autodocs"]},"inputs-buttons-solid-button--status":{"type":"story","id":"inputs-buttons-solid-button--status","name":"Status","title":"Inputs/Buttons/Solid Button","importPath":"./stories/Button.stories.js","tags":["dev","test","autodocs"]},"inputs-buttons-solid-button--leading-icon":{"type":"story","id":"inputs-buttons-solid-button--leading-icon","name":"Leading Icon","title":"Inputs/Buttons/Solid Button","importPath":"./stories/Button.stories.js","tags":["dev","test","autodocs"]},"inputs-buttons-solid-button--trailing-icon":{"type":"story","id":"inputs-buttons-solid-button--trailing-icon","name":"Trailing Icon","title":"Inputs/Buttons/Solid Button","importPath":"./stories/Button.stories.js","tags":["dev","test","autodocs"]},"inputs-buttons-solid-button--icon-on-both-sides":{"type":"story","id":"inputs-buttons-solid-button--icon-on-both-sides","name":"Icon On Both Sides","title":"Inputs/Buttons/Solid Button","importPath":"./stories/Button.stories.js","tags":["dev","test","autodocs"]},"inputs-buttons-icon-button--docs":{"id":"inputs-buttons-icon-button--docs","title":"Inputs/Buttons/Icon Button","name":"Docs","importPath":"./stories/IconButton.stories.js","type":"docs","tags":["dev","test","autodocs"],"storiesImports":[]},"inputs-buttons-icon-button--default":{"type":"story","id":"inputs-buttons-icon-button--default","name":"Default","title":"Inputs/Buttons/Icon Button","importPath":"./stories/IconButton.stories.js","tags":["dev","test","autodocs"]},"inputs-buttons-icon-button--size":{"type":"story","id":"inputs-buttons-icon-button--size","name":"Size","title":"Inputs/Buttons/Icon Button","importPath":"./stories/IconButton.stories.js","tags":["dev","test","autodocs"]},"inputs-buttons-icon-button--status":{"type":"story","id":"inputs-buttons-icon-button--status","name":"Status","title":"Inputs/Buttons/Icon Button","importPath":"./stories/IconButton.stories.js","tags":["dev","test","autodocs"]},"inputs-input--docs":{"id":"inputs-input--docs","title":"Inputs/Input","name":"Docs","importPath":"./stories/Input.stories.js","type":"docs","tags":["dev","test","autodocs"],"storiesImports":[]},"inputs-input--default":{"type":"story","id":"inputs-input--default","name":"Default","title":"Inputs/Input","importPath":"./stories/Input.stories.js","tags":["dev","test","autodocs"]},"inputs-input--password":{"type":"story","id":"inputs-input--password","name":"Password","title":"Inputs/Input","importPath":"./stories/Input.stories.js","tags":["dev","test","autodocs"]},"inputs-input--with-help-text":{"type":"story","id":"inputs-input--with-help-text","name":"With Help Text","title":"Inputs/Input","importPath":"./stories/Input.stories.js","tags":["dev","test","autodocs"]},"inputs-input--hidden-label":{"type":"story","id":"inputs-input--hidden-label","name":"Hidden Label","title":"Inputs/Input","importPath":"./stories/Input.stories.js","tags":["dev","test","autodocs"]},"inputs-input--full-width":{"type":"story","id":"inputs-input--full-width","name":"Full Width","title":"Inputs/Input","importPath":"./stories/Input.stories.js","tags":["dev","test","autodocs"]},"inputs-input--status":{"type":"story","id":"inputs-input--status","name":"Status","title":"Inputs/Input","importPath":"./stories/Input.stories.js","tags":["dev","test","autodocs"]},"atoms-stack--docs":{"id":"atoms-stack--docs","title":"Atoms/Stack","name":"Docs","importPath":"./stories/Stack.stories.js","type":"docs","tags":["dev","test","autodocs"],"storiesImports":[]},"atoms-stack--preview":{"type":"story","id":"atoms-stack--preview","name":"Preview","title":"Atoms/Stack","importPath":"./stories/Stack.stories.js","tags":["dev","test","autodocs"]},"atoms-stack--direction":{"type":"story","id":"atoms-stack--direction","name":"Direction","title":"Atoms/Stack","importPath":"./stories/Stack.stories.js","tags":["dev","test","autodocs"]},"atoms-stack--gap":{"type":"story","id":"atoms-stack--gap","name":"Gap","title":"Atoms/Stack","importPath":"./stories/Stack.stories.js","tags":["dev","test","autodocs"]},"atoms-stack--width":{"type":"story","id":"atoms-stack--width","name":"Width","title":"Atoms/Stack","importPath":"./stories/Stack.stories.js","tags":["dev","test","autodocs"]},"atoms-stack--positioning":{"type":"story","id":"atoms-stack--positioning","name":"Positioning","title":"Atoms/Stack","importPath":"./stories/Stack.stories.js","tags":["dev","test","autodocs"]},"atoms-text--docs":{"id":"atoms-text--docs","title":"Atoms/Text","name":"Docs","importPath":"./stories/Text.stories.js","type":"docs","tags":["dev","test","autodocs"],"storiesImports":[]},"atoms-text--default":{"type":"story","id":"atoms-text--default","name":"Default","title":"Atoms/Text","importPath":"./stories/Text.stories.js","tags":["dev","test","autodocs"]},"atoms-text--weight":{"type":"story","id":"atoms-text--weight","name":"Weight","title":"Atoms/Text","importPath":"./stories/Text.stories.js","tags":["dev","test","autodocs"]},"atoms-text--size":{"type":"story","id":"atoms-text--size","name":"Size","title":"Atoms/Text","importPath":"./stories/Text.stories.js","tags":["dev","test","autodocs"]},"atoms-text--leading":{"type":"story","id":"atoms-text--leading","name":"Leading","title":"Atoms/Text","importPath":"./stories/Text.stories.js","tags":["dev","test","autodocs"]},"inputs-buttons-text-button--docs":{"id":"inputs-buttons-text-button--docs","title":"Inputs/Buttons/Text Button","name":"Docs","importPath":"./stories/TextButton.stories.js","type":"docs","tags":["dev","test","autodocs"],"storiesImports":[]},"inputs-buttons-text-button--default":{"type":"story","id":"inputs-buttons-text-button--default","name":"Default","title":"Inputs/Buttons/Text Button","importPath":"./stories/TextButton.stories.js","tags":["dev","test","autodocs"]},"inputs-buttons-text-button--intent":{"type":"story","id":"inputs-buttons-text-button--intent","name":"Intent","title":"Inputs/Buttons/Text Button","importPath":"./stories/TextButton.stories.js","tags":["dev","test","autodocs"]},"inputs-buttons-text-button--size":{"type":"story","id":"inputs-buttons-text-button--size","name":"Size","title":"Inputs/Buttons/Text Button","importPath":"./stories/TextButton.stories.js","tags":["dev","test","autodocs"]},"inputs-buttons-text-button--status":{"type":"story","id":"inputs-buttons-text-button--status","name":"Status","title":"Inputs/Buttons/Text Button","importPath":"./stories/TextButton.stories.js","tags":["dev","test","autodocs"]},"inputs-buttons-text-button--leading-icon":{"type":"story","id":"inputs-buttons-text-button--leading-icon","name":"Leading Icon","title":"Inputs/Buttons/Text Button","importPath":"./stories/TextButton.stories.js","tags":["dev","test","autodocs"]},"inputs-buttons-text-button--trailing-icon":{"type":"story","id":"inputs-buttons-text-button--trailing-icon","name":"Trailing Icon","title":"Inputs/Buttons/Text Button","importPath":"./stories/TextButton.stories.js","tags":["dev","test","autodocs"]},"inputs-buttons-text-button--icon-on-both-sides":{"type":"story","id":"inputs-buttons-text-button--icon-on-both-sides","name":"Icon On Both Sides","title":"Inputs/Buttons/Text Button","importPath":"./stories/TextButton.stories.js","tags":["dev","test","autodocs"]}}}
